wagtail_localize_intentional_blanks/__init__.py
wagtail_localize_intentional_blanks/apps.py
wagtail_localize_intentional_blanks/constants.py
wagtail_localize_intentional_blanks/patch.py
wagtail_localize_intentional_blanks/urls.py
wagtail_localize_intentional_blanks/utils.py
wagtail_localize_intentional_blanks/views.py
wagtail_localize_intentional_blanks/wagtail_hooks.py
wagtail_localize_intentional_blanks/static/wagtail_localize_intentional_blanks/css/translation-editor.css
wagtail_localize_intentional_blanks/static/wagtail_localize_intentional_blanks/js/translation-editor.js
wagtail_localize_intentional_blanks/templates/wagtail_localize/admin/edit_translation.html
wagtail_localize_intentional_blanks/templatetags/__init__.py
wagtail_localize_intentional_blanks/templatetags/intentional_blanks.py
wagtail_localize_intentional_blanks-0.2.4.dist-info/licenses/LICENSE
wagtail_localize_intentional_blanks-0.2.4.dist-info/METADATA
wagtail_localize_intentional_blanks-0.2.4.dist-info/WHEEL
wagtail_localize_intentional_blanks-0.2.4.dist-info/top_level.txt
wagtail_localize_intentional_blanks-0.2.4.dist-info/RECORD
