Metadata-Version: 2.4
Name: wagtail-localize-intentional-blanks
Version: 0.2.4
Summary: Allow translators to mark wagtail-localize segments as 'do not translate'
Author-email: "Lincoln Loop, LLC" <info@lincolnloop.com>
License: MIT
Project-URL: Homepage, https://github.com/lincolnloop/wagtail-localize-intentional-blanks
Project-URL: Documentation, https://github.com/lincolnloop/wagtail-localize-intentional-blanks
Project-URL: Repository, https://github.com/lincolnloop/wagtail-localize-intentional-blanks
Project-URL: Bug Tracker, https://github.com/lincolnloop/wagtail-localize-intentional-blanks/issues
Classifier: Development Status :: 3 - Alpha
Classifier: Framework :: Django
Classifier: Framework :: Django :: 4.2
Classifier: Framework :: Django :: 5.0
Classifier: Framework :: Wagtail
Classifier: Framework :: Wagtail :: 5
Classifier: Framework :: Wagtail :: 6
Classifier: Intended Audience :: Developers
Classifier: License :: OSI Approved :: MIT License
Classifier: Operating System :: OS Independent
Classifier: Programming Language :: Python :: 3
Classifier: Programming Language :: Python :: 3.10
Classifier: Programming Language :: Python :: 3.11
Classifier: Programming Language :: Python :: 3.12
Classifier: Programming Language :: Python :: 3.13
Classifier: Topic :: Software Development :: Internationalization
Requires-Python: >=3.10
License-File: LICENSE
Requires-Dist: Django>=4.2
Requires-Dist: wagtail>=5.2
Requires-Dist: wagtail-localize>=1.8
Provides-Extra: dev
Requires-Dist: pytest>=7.0; extra == "dev"
Requires-Dist: pytest-django>=4.5; extra == "dev"
Requires-Dist: pytest-cov>=4.0; extra == "dev"
Requires-Dist: selenium>=4.0; extra == "dev"
Requires-Dist: pillow>=10.0; extra == "dev"
Requires-Dist: black>=23.0; extra == "dev"
Requires-Dist: flake8>=6.0; extra == "dev"
Requires-Dist: isort>=5.12; extra == "dev"
Requires-Dist: mypy>=1.0; extra == "dev"
Provides-Extra: docs
Requires-Dist: mkdocs>=1.5; extra == "docs"
Requires-Dist: mkdocs-material>=9.0; extra == "docs"
Dynamic: license-file
